fsc/async_tools/__init__.py
fsc/async_tools/_batch_submit.py
fsc/async_tools/_periodic_task.py
fsc/async_tools/_version.py
fsc/async_tools/_wrap_to_coroutine.py
fsc/async_tools/version.txt
fsc.async_tools-0.3.0.dist-info/METADATA
fsc.async_tools-0.3.0.dist-info/RECORD
fsc.async_tools-0.3.0.dist-info/WHEEL
fsc.async_tools-0.3.0.dist-info/top_level.txt
